alacorder/__main__.py
alacorder/alac.py
alacorder/run.py
alacorder_ppy-6.6.dist-info/LICENSE
alacorder_ppy-6.6.dist-info/METADATA
alacorder_ppy-6.6.dist-info/WHEEL
alacorder_ppy-6.6.dist-info/top_level.txt
alacorder_ppy-6.6.dist-info/RECORD
